absstream/__init__.py
absstream/stream.py
tests/__init__.py
tests/stream.py
absstream-1.0.6.dist-info/LICENSE.txt
absstream-1.0.6.dist-info/METADATA
absstream-1.0.6.dist-info/WHEEL
absstream-1.0.6.dist-info/top_level.txt
absstream-1.0.6.dist-info/RECORD
