Metadata-Version: 2.1
Name: absstream
Version: 1.0.6
Summary: Abstract Stream
Home-page: https://github.com/narupo/absstream
Author: narupo
Author-email: narupo.glab@gmail.com
License: MIT
Keywords: absstream
Platform: UNKNOWN
Classifier: License :: OSI Approved :: MIT License
Classifier: Programming Language :: Python :: 3.5
Classifier: Programming Language :: Python :: 3.6
